MathcadPy/__init__.py
MathcadPy/__version__.py
MathcadPy/_application.py
MathcadPy/util.py
MathcadPy-0.5.dist-info/LICENSE
MathcadPy-0.5.dist-info/METADATA
MathcadPy-0.5.dist-info/WHEEL
MathcadPy-0.5.dist-info/entry_points.txt
MathcadPy-0.5.dist-info/top_level.txt
MathcadPy-0.5.dist-info/RECORD
