Metadata-Version: 2.2
Name: MathcadPy
Version: 0.5
Summary: A Python wrapper for the Mathcad Prime COM API
Home-page: https://github.com/MattWoodhead/MathcadPy
Author: Matt Woodhead
Author-email: ol9pzgqux@mozmail.com
License: GNU GPL v3.0
Keywords: Mathcad,automation,COM,windows
Classifier: Development Status :: 5 - Production/Stable
Classifier: Intended Audience :: Developers
Classifier: Programming Language :: Python :: 3.6
Classifier: Environment :: Win32 (MS Windows)
Classifier: License :: OSI Approved :: GNU General Public License v3 (GPLv3)
Requires-Python: >3.5
License-File: LICENSE
Requires-Dist: pywin32
Dynamic: author
Dynamic: author-email
Dynamic: classifier
Dynamic: description
Dynamic: description-content-type
Dynamic: home-page
Dynamic: keywords
Dynamic: license
Dynamic: requires-dist
Dynamic: requires-python
Dynamic: summary
